{
  "report_for": {
    "en": "Accessibility Conformance Report for ",
    "nl": "Rapport: toegankelijkheid van "
  },
  "evaluated_by": {
    "en": "Evaluated by",
    "nl": "Onderzocht door"
  },
  "commissioned_by": {
    "en": "Commissioned by",
    "nl": "In opdracht van"
  },
  "target": {
    "en": "Target",
    "nl": "Conformiteitsdoel"
  },
  "date": {
    "en": "Date",
    "nl": "Datum"
  },
  "special_requirements": {
    "en": "Special requirements",
    "nl": "Speciale eisen"
  },
  "scope": {
    "en": "Scope",
    "nl": "Scope"
  },
  "scope_items": {
    "en": "Pages",
    "nl": "Pagina's"
  },
  "sample": {
    "en": "Sample",
    "nl": "Sample"
  },
  "representative_sample": {
    "en": "Representative sample",
    "nl": "Voor dit onderzoek zijn de volgende pagina's gebruikt als representatieve steekproef van de onderzochte website:"
  },
  "not_in_scope": {
    "en": "Not in scope",
    "nl": "Niet in scope"
  },
  "issue": {
    "en": "Issue",
    "nl": "Bevinding"
  },
  "issues": {
    "en": "Issues",
    "nl": "Bevindingen"
  },
  "wcag_criterion": {
    "en": "WCAG criterion",
    "nl": "WCAG criterium"
  },
  "severity": {
    "en": "Severity",
    "nl": "Ernst"
  },
  "difficulty": {
    "en": "Difficulty",
    "nl": "Complexiteit"
  },
  "executive_summary": {
    "en": "Executive summary",
    "nl": "Samenvatting"
  },
  "about_this_report": {
    "en": "About this report",
    "nl": "Toelichting bij dit rapport"
  },
  "principle": {
    "en": "Principle",
    "nl": "Principe"
  },
  "perceivable": {
    "en": "Perceivable",
    "nl": "Waarneembaar"
  },
  "operable": {
    "en": "Operable",
    "nl": "Bedienbaar"
  },
  "understandable": {
    "en": "Understandable",
    "nl": "Begrijpelijk"
  },
  "robust": {
    "en": "Robust",
    "nl": "Robuust"
  },
  "results_per_principle": {
    "en": "Results by principle",
    "nl": "Resultaten per principe"
  },
  "total": {
    "en": "Total",
    "nl": "Totaal"
  },
  "of": {
    "en": "of",
    "nl": "uit"
  },
  "all_pages": {
    "en": "All pages",
    "nl": "Alle pagina's"
  },
  "accessibility_support": {
    "en": "Accessibility support",
    "nl": "Ondersteuning"
  },
  "technologies_used": {
    "en": "Technologies used",
    "nl": "Gebruikte technologieën"
  },
  "accessibility_support_explanation": {
    "en": "The audited website should work in at least the following browsers and assistive technologies: ",
    "nl": "De onderzochte website zou minimaal moeten kunnen worden gebruikt in de volgende browsers en hulptechnologieën:"
  },
  "technologies_explanation": {
    "en": "The audited web page relies on the following technologies: ",
    "nl": "De onderzochte maakt gebruik van de volgende technologieën: "
  },
  "tip": {
    "en": "Tip",
    "nl": "Tip"
  },
  "external_link": {
    "en": "external link",
    "nl": "externe link"
  },
  "base_uri": {
    "en": "https://www.w3.org/WAI/WCAG21/quickref/?versions=2.1",
    "nl": "https://www.w3.org/Translations/WCAG21-nl"
  }
}